monom/__init__.py
monom/fields.py
monom/helpers.py
monom/model.py
monom/mongo.py
monom/utils.py
monom-1.1.0.dist-info/LICENSE
monom-1.1.0.dist-info/METADATA
monom-1.1.0.dist-info/WHEEL
monom-1.1.0.dist-info/top_level.txt
monom-1.1.0.dist-info/RECORD
