Metadata-Version: 2.1
Name: monom
Version: 1.1.0
Summary: An object mapper for MongoDB with type hints.
Home-page: https://github.com/cymoo/monom
Author: cymoo
Author-email: wakenee@hotmail.com
License: MIT
Platform: any
Classifier: Development Status :: 4 - Beta
Classifier: Operating System :: OS Independent
Classifier: Intended Audience :: Developers
Classifier: License :: OSI Approved :: MIT License
Classifier: Programming Language :: Python :: 3
Classifier: Programming Language :: Python :: 3.6
Classifier: Programming Language :: Python :: 3.7
Classifier: Programming Language :: Python :: 3.8
Classifier: Topic :: Database
Classifier: Topic :: Utilities
Classifier: Topic :: Software Development :: Libraries :: Python Modules
Requires-Python: >=3.6
Requires-Dist: pymongo (>=3.7)
Provides-Extra: dev
Requires-Dist: pytest ; extra == 'dev'
